cloudrail/dev_tools/__init__.py
cloudrail/dev_tools/aws_rule_test_utils.py
cloudrail/dev_tools/rule_test_utils.py
cloudrail/knowledge/__init__.py
cloudrail/knowledge/exceptions.py
cloudrail/knowledge/context/__init__.py
cloudrail/knowledge/context/aliases_dict.py
cloudrail/knowledge/context/base_environment_context.py
cloudrail/knowledge/context/cloneable.py
cloudrail/knowledge/context/cloud_provider.py
cloudrail/knowledge/context/connection.py
cloudrail/knowledge/context/field_active.py
cloudrail/knowledge/context/iac_action_type.py
cloudrail/knowledge/context/iac_resource_metadata.py
cloudrail/knowledge/context/iac_state.py
cloudrail/knowledge/context/iac_type.py
cloudrail/knowledge/context/ip_protocol.py
cloudrail/knowledge/context/managed_resources_summary.py
cloudrail/knowledge/context/mergeable.py
cloudrail/knowledge/context/unknown_block.py
cloudrail/knowledge/context/aws/__init__.py
cloudrail/knowledge/context/aws/aws_cloudformation_environment_context_builder.py
cloudrail/knowledge/context/aws/aws_connection_builder.py
cloudrail/knowledge/context/aws/aws_environment_context.py
cloudrail/knowledge/context/aws/aws_environment_context_defaults_merger.py
cloudrail/knowledge/context/aws/aws_environment_context_enrichment.py
cloudrail/knowledge/context/aws/aws_relations_assigner.py
cloudrail/knowledge/context/aws/aws_resource_enrichment.py
cloudrail/knowledge/context/aws/aws_terraform_environment_context_builder.py
cloudrail/knowledge/context/aws/predefind_components.py
cloudrail/knowledge/context/aws/pseudo_builder.py
cloudrail/knowledge/context/aws/resources_assigner_util.py
cloudrail/knowledge/context/aws/service_ip_range.py
cloudrail/knowledge/context/aws/cloudformation/__init__.py
cloudrail/knowledge/context/aws/cloudformation/aws_cloudformation_context_builder.py
cloudrail/knowledge/context/aws/cloudformation/cloudformation_constants.py
cloudrail/knowledge/context/aws/cloudformation/cloudformation_fields.yaml
cloudrail_knowledge-0.0.228.dist-info/LICENSE
cloudrail_knowledge-0.0.228.dist-info/METADATA
cloudrail_knowledge-0.0.228.dist-info/WHEEL
cloudrail_knowledge-0.0.228.dist-info/top_level.txt
cloudrail_knowledge-0.0.228.dist-info/RECORD
