Metadata-Version: 2.1
Name: cloudrail-knowledge
Version: 0.0.228
Summary: Cloudrail's package for security rules
Home-page: https://github.com/indeni/cloudrail-knowledge
Author: Indeni
Author-email: engineering@indeni.com
License: UNKNOWN
Keywords: cloud,aws,azure,security,rules,checks
Platform: UNKNOWN
Classifier: Development Status :: 3 - Alpha
Classifier: Intended Audience :: Developers
Classifier: License :: OSI Approved :: MIT License
Classifier: Programming Language :: Python :: 3.7
Classifier: Programming Language :: Python :: 3.8
Classifier: Programming Language :: Python :: 3.9
Classifier: Topic :: Security
Classifier: Topic :: Software Development :: Build Tools
License-File: LICENSE
Requires-Dist: arnparse (==0.0.2)
Requires-Dist: boto3
Requires-Dist: netaddr (==0.7.19)
Requires-Dist: dataclasses-json (==0.5.2)
Requires-Dist: PyYAML (==5.4.1)
Requires-Dist: packaging
Requires-Dist: cfn-tools
Requires-Dist: backoff
Requires-Dist: requests (>=2.22.0)
Requires-Dist: deepdiff
Requires-Dist: rsa
Requires-Dist: natsort
Requires-Dist: cfn-flip
